SimpleText/__init__.py
SimpleText/preprocessor.py
SimpleText-1.0.3.dist-info/LICENSE
SimpleText-1.0.3.dist-info/METADATA
SimpleText-1.0.3.dist-info/WHEEL
SimpleText-1.0.3.dist-info/top_level.txt
SimpleText-1.0.3.dist-info/RECORD
