Metadata-Version: 2.1
Name: SimpleText
Version: 1.0.3
Summary: A package to manage textual data in a simple fashion.
Home-page: https://github.com/Paresh95/SimpleText
Author: Paresh Sharma
Author-email: paresh7903@gmail.com
License: UNKNOWN
Keywords: Pre-processing,Text Analysis,NLP
Platform: UNKNOWN
Classifier: Programming Language :: Python :: 3
Classifier: License :: OSI Approved :: MIT License
Classifier: Operating System :: OS Independent
Requires-Python: >=3.6
